waffle/__init__.py
waffle/api/__init__.py
waffle/api/abc.py
waffle/api/api.py
waffle/api/request_validator/__init__.py
waffle/api/request_validator/abc.py
waffle/api/request_validator/translate_friendly_types_validator.py
waffle/api/response_validator/__init__.py
waffle/api/response_validator/abc.py
waffle/api/response_validator/telegram_api_error_validator.py
waffle/api/utils/__init__.py
waffle/api/utils/file_util.py
waffle/api/utils/token_util.py
waffle/bot/__init__.py
waffle/bot/abc.py
waffle/bot/blueprint/__init__.py
waffle/bot/blueprint/abc.py
waffle/bot/blueprint/bot.py
waffle/bot/bot.py
waffle/bot/dispatch/__init__.py
waffle/bot/dispatch/handlers/__init__.py
waffle/bot/dispatch/handlers/abc.py
waffle/bot/dispatch/handlers/func.py
waffle/bot/dispatch/labelers/__init__.py
waffle/bot/dispatch/labelers/abc.py
waffle/bot/dispatch/labelers/default.py
waffle/bot/dispatch/middlewares/__init__.py
waffle/bot/dispatch/middlewares/base.py
waffle/bot/dispatch/return_manager/__init__.py
waffle/bot/dispatch/return_manager/abc.py
waffle/bot/dispatch/return_manager/message.py
waffle/bot/dispatch/router/__init__.py
waffle/bot/dispatch/router/abc.py
waffle/bot/dispatch/router/bot.py
waffle/bot/dispatch/view/__init__.py
waffle/bot/dispatch/view/abc.py
waffle/bot/dispatch/view/message.py
waffle/bot/dispatch/view/raw.py
waffle/bot/polling/__init__.py
waffle/bot/polling/abc.py
waffle/bot/polling/bot.py
waffle/bot/rules/__init__.py
waffle/bot/rules/abc.py
waffle/bot/rules/base.py
waffle/bot/rules/callback_query.py
waffle/bot/rules/message.py
waffle/bot/states/__init__.py
waffle/bot/states/dispenser/__init__.py
waffle/bot/states/dispenser/abc.py
waffle/bot/states/dispenser/default.py
waffle/bot/states/types.py
waffle/bot/updates/__init__.py
waffle/bot/updates/base.py
waffle/bot/updates/types.py
waffle/contrib/__init__.py
waffle/contrib/rules/__init__.py
waffle/contrib/storage/__init__.py
waffle/errors/__init__.py
waffle/errors/base_exceptions.py
waffle/errors/code_exception.py
wondergram-0.1.1.dist-info/LICENSE
wondergram-0.1.1.dist-info/WHEEL
wondergram-0.1.1.dist-info/METADATA
wondergram-0.1.1.dist-info/RECORD
